MANIFEST.in
README.rst
setup.py
slpy/__init__.py
slpy/command_line.py
slpy/sl.c
slpy/sl.h
slpy/slpyc.c
slpy.egg-info/PKG-INFO
slpy.egg-info/SOURCES.txt
slpy.egg-info/dependency_links.txt
slpy.egg-info/entry_points.txt
slpy.egg-info/top_level.txt
slpy.egg-info/zip-safe