Metadata-Version: 1.1
Name: slpy
Version: 1.5.2
Summary: SL for python
Home-page: https://github.com/linnil1/sl
Author: linnil1
Author-email: linnil1.886@gmail.com
License: MIT
Keywords: sl
Platform: UNKNOWN
Classifier: Programming Language :: Python :: 3.5
